pythoncom.py
pywin32.pth
isapi/PyISAPI_loader.dll
isapi/README.txt
isapi/__init__.py
isapi/install.py
isapi/isapicon.py
isapi/simple.py
isapi/threaded_extension.py
isapi/doc/isapi.html
isapi/samples/README.txt
isapi/samples/advanced.py
isapi/samples/redirector.py
isapi/samples/redirector_asynch.py
isapi/samples/redirector_with_filter.py
isapi/samples/test.py
isapi/test/README.txt
isapi/test/extension_simple.py
pythonwin/Pythonwin.exe
pythonwin/dde.pyd
pythonwin/license.txt
pythonwin/scintilla.dll
pythonwin/win32ui.pyd
pythonwin/pywin/IDLE.cfg
pythonwin/pywin/__init__.py
pythonwin/pywin/default.cfg
pythonwin/pywin/Demos/cmdserver.py
pythonwin/pywin/Demos/createwin.py
pythonwin/pywin/Demos/demoutils.py
pythonwin/pywin/Demos/dibdemo.py
pythonwin/pywin/Demos/dlgtest.py
pythonwin/pywin/Demos/dyndlg.py
pythonwin/pywin/Demos/fontdemo.py
pythonwin/pywin/Demos/guidemo.py
pythonwin/pywin/Demos/hiertest.py
pythonwin/pywin/Demos/menutest.py
pythonwin/pywin/Demos/objdoc.py
pythonwin/pywin/Demos/openGLDemo.py
pythonwin/pywin/Demos/progressbar.py
pythonwin/pywin/Demos/sliderdemo.py
pythonwin/pywin/Demos/splittst.py
pythonwin/pywin/Demos/threadedgui.py
pythonwin/pywin/Demos/toolbar.py
pythonwin/pywin/Demos/app/basictimerapp.py
pythonwin/pywin/Demos/app/customprint.py
pythonwin/pywin/Demos/app/demoutils.py
pythonwin/pywin/Demos/app/dlgappdemo.py
pythonwin/pywin/Demos/app/dojobapp.py
pythonwin/pywin/Demos/app/helloapp.py
pythonwin/pywin/Demos/ocx/__init__.py
pythonwin/pywin/Demos/ocx/demoutils.py
pythonwin/pywin/Demos/ocx/flash.py
pythonwin/pywin/Demos/ocx/msoffice.py
pythonwin/pywin/Demos/ocx/ocxserialtest.py
pythonwin/pywin/Demos/ocx/ocxtest.py
pythonwin/pywin/Demos/ocx/webbrowser.py
pythonwin/pywin/debugger/__init__.py
pythonwin/pywin/debugger/configui.py
pythonwin/pywin/debugger/dbgcon.py
pythonwin/pywin/debugger/dbgpyapp.py
pythonwin/pywin/debugger/debugger.py
pythonwin/pywin/debugger/fail.py
win32ext-221.2.dist-info/DESCRIPTION.rst
win32ext-221.2.dist-info/METADATA
win32ext-221.2.dist-info/RECORD
win32ext-221.2.dist-info/WHEEL
win32ext-221.2.dist-info/metadata.json
win32ext-221.2.dist-info/top_level.txt
