Metadata-Version: 2.0
Name: win32ext
Version: 221.2
Summary: Python for Window Extensions
Home-page: http://sourceforge.net/projects/pywin32/
Author: Mark Hammond (et al)
Author-email: mhammond@users.sourceforge.net
License: PSF
Platform: UNKNOWN
Requires-Dist: adodbapi
Requires-Dist: win32compat
Requires-Dist: win32core
